{
  "weasels": {
    "qing": {
      "sha": "485b7a18e71bb73aef5d16f9b0d328af689d6527",
      "ref": "master",
      "url": "https://github.com/a810439322/weasel.git",
      "checked_at": "2026-07-04T20:12:10Z"
    },
    "rime": {
      "sha": "f9203cae5e2b0796d94575b975f62a6be9614b00",
      "ref": "master",
      "url": "https://github.com/rime/weasel.git",
      "checked_at": "2026-07-04T20:12:10Z"
    },
    "fxliang": {
      "sha": "733731a81eab8239576b07c4491b9f831b1110c2",
      "ref": "pb",
      "url": "https://github.com/fxliang/weasel.git",
      "checked_at": "2026-07-04T20:12:10Z"
    }
  },
  "datas": {
    "jdhe": {
      "sha": "37787aee904f74059f470905633c99031d258475",
      "ref": "main",
      "url": "https://github.com/rimeinn/rime-JDhe.git",
      "checked_at": "2026-07-04T20:12:10Z"
    },
    "snow-pinyin": {
      "sha": "082b2e88c295102d73fe768814dcf51b0b0e286e",
      "ref": "main",
      "url": "https://github.com/rimeinn/rime-snow-pinyin.git",
      "checked_at": "2026-07-04T20:12:10Z"
    },
    "moran-trad": {
      "sha": "8c247cc43f003cef82e681c4f8cbe8869c4f8e61",
      "ref": "trad",
      "url": "https://github.com/rimeinn/rime-moran.git",
      "checked_at": "2026-07-04T20:12:10Z"
    },
    "kagiroi": {
      "sha": "1951bab3742495f763b79809af253884c33358e9",
      "ref": "main",
      "url": "https://github.com/rimeinn/rime-kagiroi.git",
      "checked_at": "2026-07-04T20:12:10Z"
    },
    "tiger": {
      "sha": "c7a5879f40dfa11b7e8ccd23aa455d871be638be",
      "ref": "main",
      "url": "https://github.com/a810439322/rime-tiger.git",
      "checked_at": "2026-07-04T20:12:10Z"
    },
    "lutai": {
      "sha": "e4d5119871e7ea677014bf749fe4174bd300b30b",
      "ref": "dev",
      "url": "https://github.com/Flauver/lutai.git",
      "checked_at": "2026-07-04T20:12:10Z"
    },
    "mungyeong": {
      "sha": "942c36bec83da5f460ac2cbc470a4ed9993cdf8f",
      "ref": "main",
      "url": "https://github.com/rimeinn/rime-mungyeong.git",
      "checked_at": "2026-07-04T20:12:10Z"
    },
    "moran-simp": {
      "sha": "4d4e24ad3c30c18e08c6032431fdbc4339f2d49f",
      "ref": "simp",
      "url": "https://github.com/rimeinn/rime-moran.git",
      "checked_at": "2026-07-04T20:12:10Z"
    },
    "openfly": {
      "sha": "f0982a96291c1d221753cf5a049778fd88ce45e2",
      "ref": "main",
      "url": "https://github.com/amorphobia/openfly.git",
      "checked_at": "2026-07-04T20:12:10Z"
    },
    "092wb": {
      "sha": "0892bd40abf32d427bd3bf91763b65d29d5ec624",
      "ref": "main",
      "url": "https://github.com/092wb/092wb.git",
      "checked_at": "2026-07-04T20:12:10Z"
    },
    "zrlong": {
      "sha": "97543f6fe0a2b2f308933c40f166a883b3f348e6",
      "ref": "main",
      "url": "https://github.com/rimeinn/rime-zrlong.git",
      "checked_at": "2026-07-04T20:12:10Z"
    },
    "crane": {
      "sha": "44d00fa68d9f4754b6381797bdbd5fcd405bfaf7",
      "ref": "main",
      "url": "https://github.com/kchen0x/rime-crane.git",
      "checked_at": "2026-07-04T20:12:10Z"
    }
  }
}